fleetvue/__init__.py
fleetvue/engine.py
fleetvue-0.1.2.dist-info/licenses/LICENSE
fleetvue-0.1.2.dist-info/METADATA
fleetvue-0.1.2.dist-info/WHEEL
fleetvue-0.1.2.dist-info/top_level.txt
fleetvue-0.1.2.dist-info/RECORD
