Metadata-Version: 2.4
Name: fleetvue
Version: 0.1.2
Summary: A Vue.js-like templating engine using Jinja2 for Python
Author-email: Vishnu Prasad <vishnuprasadowe@gmail.com>
License: MIT
Project-URL: Homepage, https://github.com/py-level/fleet
Project-URL: Documentation, https://github.com/py-level/fleet#readme
Project-URL: Repository, https://github.com/py-level/fleet
Project-URL: Bug Tracker, https://github.com/py-level/fleet/issues
Keywords: vue,jinja2,templating,html,template-engine
Classifier: Development Status :: 4 - Beta
Classifier: Intended Audience :: Developers
Classifier: License :: OSI Approved :: MIT License
Classifier: Operating System :: OS Independent
Classifier: Programming Language :: Python :: 3
Classifier: Programming Language :: Python :: 3.7
Classifier: Programming Language :: Python :: 3.8
Classifier: Programming Language :: Python :: 3.9
Classifier: Programming Language :: Python :: 3.10
Classifier: Topic :: Software Development :: Libraries :: Python Modules
Classifier: Topic :: Text Processing :: Markup :: HTML
Requires-Python: >=3.7
License-File: LICENSE
Requires-Dist: beautifulsoup4>=4.9.3
Requires-Dist: jinja2>=3.0.0
Dynamic: license-file
